svg_collector/main.py
svg_collector-0.1.3.dist-info/METADATA
svg_collector-0.1.3.dist-info/WHEEL
svg_collector-0.1.3.dist-info/entry_points.txt
svg_collector-0.1.3.dist-info/RECORD
